Workbook

Sheet 1- EU Base Rates
A1: Participant type | B1: EU base rates (%)
A2: Other | B2: 0.25
A3: Profit | B3: 0.35
A4: Non-profit | B4: 0.5
A5: SME | B5: 0.5
A6: [other] | B6: […%]

Sheet 2 - National Top-up Rates
A1: Country | B1: Participant type | C1: National top-up rate
A2: Malta | B2: Profit | C2: 0.35
A3: Sweden | B3: SME | C3: 0.55
A4: Malta | B4: Non-profit | C4: 0.5

Sheet 3 - Funding Rate per Particpant
A1: Individual funding rates per participant | L1: Grant breakdown
A2: No | B2: Short name | C2: Country | D2: Participant type | E2: EU base rate | F2: National top-up rate | G2: Total funding rate | H2: Total costs | I2: Maximum EU contribution | J2: Requested EU contribution | L2: EU funding | M2: National contribution top-up
A3: 1 | B3: BEN1 | C3: Norway | D3: Profit | E3: =_xlfn.IFNA(VLOOKUP(Table4[[#This Row],[Participant type]],Table1[],2,FALSE),"N/A") -> 0.35 | F3: =_xlfn.IFNA(INDEX(Table3[National top-up rate],(MATCH(C3,Table3[Country],0)*MATCH(D3,Table3[Participant type],0)),0),"N/A") -> N/A | G3: =IFERROR(Table4[[#This Row],[EU base rate]]+IF(Table4[[#This Row],[National top-up rate]]<>"N/A",Table4[[#This Row],[National top-up rate]],0),"N/A") -> 0.35 | I3: =IFERROR(Table4[[#This Row],[Total costs]]*Table4[[#This Row],[Total funding rate]],"N/A") -> 0 | L3: =IFERROR(Table4[[#This Row],[EU base rate]]*Table4[[#This Row],[Total costs]],0) -> 0 | M3: =IFERROR((Table4[[#This Row],[National top-up rate]])*Table4[[#This Row],[Total costs]],0) -> 0
A4: 1.1 | B4: AE1 | C4: Malta | D4: Non-profit | E4: =_xlfn.IFNA(VLOOKUP(Table4[[#This Row],[Participant type]],Table1[],2,FALSE),"N/A") -> 0.5 | F4: =_xlfn.IFNA(INDEX(Table3[National top-up rate],(MATCH(C4,Table3[Country],0)*MATCH(D4,Table3[Participant type],0)),0),"N/A") -> 0.5 | G4: =IFERROR(Table4[[#This Row],[EU base rate]]+IF(Table4[[#This Row],[National top-up rate]]<>"N/A",Table4[[#This Row],[National top-up rate]],0),"N/A") -> 1 | I4: =IFERROR(Table4[[#This Row],[Total costs]]*Table4[[#This Row],[Total funding rate]],"N/A") -> 0 | L4: =IFERROR(Table4[[#This Row],[EU base rate]]*Table4[[#This Row],[Total costs]],0) -> 0 | M4: =IFERROR((Table4[[#This Row],[National top-up rate]])*Table4[[#This Row],[Total costs]],0) -> 0
A5: 2 | B5: BEN2 | C5: Denmark | D5: Other | E5: =_xlfn.IFNA(VLOOKUP(Table4[[#This Row],[Participant type]],Table1[],2,FALSE),"N/A") -> 0.25 | F5: =_xlfn.IFNA(INDEX(Table3[National top-up rate],(MATCH(C5,Table3[Country],0)*MATCH(D5,Table3[Participant type],0)),0),"N/A") -> N/A | G5: =IFERROR(Table4[[#This Row],[EU base rate]]+IF(Table4[[#This Row],[National top-up rate]]<>"N/A",Table4[[#This Row],[National top-up rate]],0),"N/A") -> 0.25 | I5: =IFERROR(Table4[[#This Row],[Total costs]]*Table4[[#This Row],[Total funding rate]],"N/A") -> 0 | L5: =IFERROR(Table4[[#This Row],[EU base rate]]*Table4[[#This Row],[Total costs]],0) -> 0 | M5: =IFERROR((Table4[[#This Row],[National top-up rate]])*Table4[[#This Row],[Total costs]],0) -> 0
E6: =_xlfn.IFNA(VLOOKUP(Table4[[#This Row],[Participant type]],Table1[],2,FALSE),"N/A") -> N/A | F6: =_xlfn.IFNA(INDEX(Table3[National top-up rate],(MATCH(C6,Table3[Country],0)*MATCH(D6,Table3[Participant type],0)),0),"N/A") -> N/A | G6: =IFERROR(Table4[[#This Row],[EU base rate]]+IF(Table4[[#This Row],[National top-up rate]]<>"N/A",Table4[[#This Row],[National top-up rate]],0),"N/A") -> N/A | I6: =IFERROR(Table4[[#This Row],[Total costs]]*Table4[[#This Row],[Total funding rate]],"N/A") -> N/A | L6: =IFERROR(Table4[[#This Row],[EU base rate]]*Table4[[#This Row],[Total costs]],0) -> 0 | M6: =IFERROR((Table4[[#This Row],[National top-up rate]])*Table4[[#This Row],[Total costs]],0) -> 0
E7: =_xlfn.IFNA(VLOOKUP(Table4[[#This Row],[Participant type]],Table1[],2,FALSE),"N/A") -> N/A | F7: =_xlfn.IFNA(INDEX(Table3[National top-up rate],(MATCH(C7,Table3[Country],0)*MATCH(D7,Table3[Participant type],0)),0),"N/A") -> N/A | G7: =IFERROR(Table4[[#This Row],[EU base rate]]+IF(Table4[[#This Row],[National top-up rate]]<>"N/A",Table4[[#This Row],[National top-up rate]],0),"N/A") -> N/A | I7: =IFERROR(Table4[[#This Row],[Total costs]]*Table4[[#This Row],[Total funding rate]],"N/A") -> N/A | L7: =IFERROR(Table4[[#This Row],[EU base rate]]*Table4[[#This Row],[Total costs]],0) -> 0 | M7: =IFERROR((Table4[[#This Row],[National top-up rate]])*Table4[[#This Row],[Total costs]],0) -> 0
E8: =_xlfn.IFNA(VLOOKUP(Table4[[#This Row],[Participant type]],Table1[],2,FALSE),"N/A") -> N/A | F8: =_xlfn.IFNA(INDEX(Table3[National top-up rate],(MATCH(C8,Table3[Country],0)*MATCH(D8,Table3[Participant type],0)),0),"N/A") -> N/A | G8: =IFERROR(Table4[[#This Row],[EU base rate]]+IF(Table4[[#This Row],[National top-up rate]]<>"N/A",Table4[[#This Row],[National top-up rate]],0),"N/A") -> N/A | I8: =IFERROR(Table4[[#This Row],[Total costs]]*Table4[[#This Row],[Total funding rate]],"N/A") -> N/A | L8: =IFERROR(Table4[[#This Row],[EU base rate]]*Table4[[#This Row],[Total costs]],0) -> 0 | M8: =IFERROR((Table4[[#This Row],[National top-up rate]])*Table4[[#This Row],[Total costs]],0) -> 0
E9: =_xlfn.IFNA(VLOOKUP(Table4[[#This Row],[Participant type]],Table1[],2,FALSE),"N/A") -> N/A | F9: =_xlfn.IFNA(INDEX(Table3[National top-up rate],(MATCH(C9,Table3[Country],0)*MATCH(D9,Table3[Participant type],0)),0),"N/A") -> N/A | G9: =IFERROR(Table4[[#This Row],[EU base rate]]+IF(Table4[[#This Row],[National top-up rate]]<>"N/A",Table4[[#This Row],[National top-up rate]],0),"N/A") -> N/A | I9: =IFERROR(Table4[[#This Row],[Total costs]]*Table4[[#This Row],[Total funding rate]],"N/A") -> N/A | L9: =IFERROR(Table4[[#This Row],[EU base rate]]*Table4[[#This Row],[Total costs]],0) -> 0 | M9: =IFERROR((Table4[[#This Row],[National top-up rate]])*Table4[[#This Row],[Total costs]],0) -> 0
A10: Consortium total | H10: =SUM(H3:H9) -> 0 | I10: =SUM(I3:I9) -> 0 | J10: =SUM(J3:J9) -> 0 | L10: =SUM(L3:L9) -> 0 | M10: =SUM(M3:M9) -> 0

Sheet 4 - Max Amount per RP
A1: Maximum amounts per participant and reporting period (these amounts will determine how much you can ask for each RP; distribute the requested grant amount in line with your planned budget consumption)
A2: No | B2: Short name | C2: Requested EU contribution | D2: RP1 | E2: RP2 | F2: RP3 | G2: … | H2: Final RP
A3: 1 | B3: BEN1 | C3: =_xlfn.IFNA(VLOOKUP(Table46[[#This Row],[Short name]],'3 - Funding Rate per Particpant'!B3:J9,9,FALSE),"N/A") -> 0
A4: 1.1 | B4: AE1 | C4: =_xlfn.IFNA(VLOOKUP(Table46[[#This Row],[Short name]],'3 - Funding Rate per Particpant'!B4:J10,9,FALSE),"N/A") -> 0
A5: 2 | B5: BEN2 | C5: =_xlfn.IFNA(VLOOKUP(Table46[[#This Row],[Short name]],'3 - Funding Rate per Particpant'!B5:J11,9,FALSE),"N/A") -> 0
C6: =_xlfn.IFNA(VLOOKUP(Table46[[#This Row],[Short name]],'3 - Funding Rate per Particpant'!B6:J12,9,FALSE),"N/A") -> N/A
C7: =_xlfn.IFNA(VLOOKUP(Table46[[#This Row],[Short name]],'3 - Funding Rate per Particpant'!B7:J13,9,FALSE),"N/A") -> N/A
C8: =_xlfn.IFNA(VLOOKUP(Table46[[#This Row],[Short name]],'3 - Funding Rate per Particpant'!B8:J14,9,FALSE),"N/A") -> N/A
C9: =_xlfn.IFNA(VLOOKUP(Table46[[#This Row],[Short name]],'3 - Funding Rate per Particpant'!B9:J15,9,FALSE),"N/A") -> N/A
A10: Consortium total | C10: =SUM(C3:C9) -> 0 | D10: =SUM(D3:D9) -> 0 | E10: =SUM(E3:E9) -> 0 | F10: =SUM(F3:F9) -> 0 | G10: =SUM(G3:G9) -> 0 | H10: =SUM(H3:H9) -> 0

Sheet 4 - Country List
A1: Country code | B1: Country name | C1: Status
A2: AT | B2: Austria | C2: EU Member State
A3: BE | B3: Belgium | C3: EU Member State
A4: BG | B4: Bulgaria | C4: EU Member State
A5: CY | B5: Cyprus | C5: EU Member State
A6: CZ | B6: Czechia | C6: EU Member State
A7: DE | B7: Germany | C7: EU Member State
A8: DK | B8: Denmark | C8: EU Member State
A9: EE | B9: Estonia | C9: EU Member State
A10: ES | B10: Spain | C10: EU Member State
A11: FI | B11: Finland | C11: EU Member State
A12: FR | B12: France | C12: EU Member State
... A46: UK | B46: United Kingdom | C46: HE Associated Country
